{
    "homepage": "https://cemu.info/",
    "version": "1.21.3",
    "license": "Freeware",
    "architecture": {
        "64bit": {
            "url": "https://cemu.info/releases/cemu_1.21.3.zip",
            "hash": "06282922d67f2421bece7a6ff6fb3299764ab0f4572a7282d4dcc62ce3217062"
        }
    },
    "extract_dir": "cemu_1.21.3",
    "shortcuts": [
        [
            "cemu.exe",
            "Cemu"
        ]
    ],
    "installer": {
        "script": [
            "if (!(Test-Path \"$persist_dir\\settings.xml\")) {",
            "    New-Item \"$dir\\settings.xml\" -Type File | Out-Null",
            "}"
        ]
    },
    "persist": [
        "settings.xml",
        "controllerProfiles",
        "gameProfiles",
        "graphicPacks",
        "mlc01"
    ],
    "suggest": {
        "vcredist": "extras/vcredist2015",
        "cemuhook": "cemuhook"
    },
    "checkver": {
        "regex": "Download latest version \\(v((?<version>[\\d.]+)[\\w]*?),"
    },
    "autoupdate": {
        "architecture": {
            "64bit": {
                "url": "https://cemu.info/releases/cemu_$matchVersion.zip"
            }
        },
        "extract_dir": "cemu_$matchVersion"
    }
}
