{
    "homepage": "https://citra-emu.org/",
    "version": "1638",
    "license": "GPL-2.0-only",
    "architecture": {
        "64bit": {
            "url": "https://github.com/citra-emu/citra-canary/releases/download/canary-1638/citra-windows-mingw-20200407-74b986c.7z",
            "hash": "fdf5fe94e67237e1c9c9eda0dea721d35fd88ff4c842c369edebfe8f34be9444"
        }
    },
    "extract_dir": "canary-mingw",
    "shortcuts": [
        [
            "citra-qt.exe",
            "Citra (Canary)"
        ]
    ],
    "bin": [
        "citra.exe",
        "citra-room.exe"
    ],
    "checkver": {
        "url": "https://github.com/citra-emu/citra-canary/releases",
        "regex": "/citra-emu/citra-canary/releases/download/canary-([\\d]+)/citra-windows-(?<env>[\\w]+)-(?<commit>[\\d]{8}-[\\da-f]{7})\\.(?<zip>7z|zip)"
    },
    "autoupdate": {
        "architecture": {
            "64bit": {
                "url": "https://github.com/citra-emu/citra-canary/releases/download/canary-$version/citra-windows-$matchEnv-$matchCommit.$matchZip"
            }
        },
        "extract_dir": "canary-$matchEnv"
    }
}
