{
    "homepage": "https://citra-emu.org/",
    "version": "1935",
    "license": "GPL-2.0-only",
    "architecture": {
        "64bit": {
            "url": "https://github.com/citra-emu/citra-canary/releases/download/canary-1935/citra-windows-mingw-20210203-ee699b2.7z",
            "hash": "60b716b552592c6d0a74591d68e8f62b69fc230213961d3933a099762e3300ff"
        }
    },
    "extract_dir": "canary-mingw",
    "shortcuts": [
        [
            "citra-qt.exe",
            "Citra (Canary)"
        ]
    ],
    "bin": [
        "citra.exe",
        "citra-room.exe"
    ],
    "checkver": {
        "url": "https://github.com/citra-emu/citra-canary/releases",
        "regex": "/citra-emu/citra-canary/releases/download/canary-([\\d]+)/citra-windows-(?<env>[\\w]+)-(?<commit>[\\d]{8}-[\\da-f]{7})\\.(?<zip>7z|zip)"
    },
    "autoupdate": {
        "architecture": {
            "64bit": {
                "url": "https://github.com/citra-emu/citra-canary/releases/download/canary-$version/citra-windows-$matchEnv-$matchCommit.$matchZip"
            }
        },
        "extract_dir": "canary-$matchEnv"
    }
}
