{
    "homepage": "https://citra-emu.org/",
    "version": "1938",
    "license": "GPL-2.0-only",
    "architecture": {
        "64bit": {
            "url": "https://github.com/citra-emu/citra-canary/releases/download/canary-1938/citra-windows-mingw-20210204-1d5dbf1.7z",
            "hash": "128bdc94b34b5fbdbe07523081c86343e5fa3e1cac81a4f07c0d363e0103d5bf"
        }
    },
    "extract_dir": "canary-mingw",
    "shortcuts": [
        [
            "citra-qt.exe",
            "Citra (Canary)"
        ]
    ],
    "bin": [
        "citra.exe",
        "citra-room.exe"
    ],
    "checkver": {
        "url": "https://github.com/citra-emu/citra-canary/releases",
        "regex": "/citra-emu/citra-canary/releases/download/canary-([\\d]+)/citra-windows-(?<env>[\\w]+)-(?<commit>[\\d]{8}-[\\da-f]{7})\\.(?<zip>7z|zip)"
    },
    "autoupdate": {
        "architecture": {
            "64bit": {
                "url": "https://github.com/citra-emu/citra-canary/releases/download/canary-$version/citra-windows-$matchEnv-$matchCommit.$matchZip"
            }
        },
        "extract_dir": "canary-$matchEnv"
    }
}
