{
    "homepage": "https://citra-emu.org/",
    "version": "1791",
    "license": "GPL-2.0-only",
    "architecture": {
        "64bit": {
            "url": "https://github.com/citra-emu/citra-canary/releases/download/canary-1791/citra-windows-mingw-20200624-0e9198e.7z",
            "hash": "fc999fc60310527d717753a0e87ba75b01235bc8d1e30313e2cc99148433c43f"
        }
    },
    "extract_dir": "canary-mingw",
    "shortcuts": [
        [
            "citra-qt.exe",
            "Citra (Canary)"
        ]
    ],
    "bin": [
        "citra.exe",
        "citra-room.exe"
    ],
    "checkver": {
        "url": "https://github.com/citra-emu/citra-canary/releases",
        "regex": "/citra-emu/citra-canary/releases/download/canary-([\\d]+)/citra-windows-(?<env>[\\w]+)-(?<commit>[\\d]{8}-[\\da-f]{7})\\.(?<zip>7z|zip)"
    },
    "autoupdate": {
        "architecture": {
            "64bit": {
                "url": "https://github.com/citra-emu/citra-canary/releases/download/canary-$version/citra-windows-$matchEnv-$matchCommit.$matchZip"
            }
        },
        "extract_dir": "canary-$matchEnv"
    }
}
