{
    "homepage": "https://yuzu-emu.org/",
    "version": "0-628",
    "license": "GPL-2.0-only",
    "architecture": {
        "64bit": {
            "url": "https://github.com/yuzu-emu/yuzu-mainline/releases/download/mainline-0-628/yuzu-windows-msvc-20210519-1a8098ac5.7z",
            "hash": "d1770c348de772efc25f211aa1ca8c4d751bf74f90e083734107a79b4dbab7ed"
        }
    },
    "extract_dir": "yuzu-windows-msvc",
    "shortcuts": [
        [
            "yuzu.exe",
            "Yuzu"
        ]
    ],
    "checkver": {
        "github": "https://github.com/yuzu-emu/yuzu-mainline",
        "regex": "download/mainline-([\\d.-]+)/yuzu-windows-msvc-(?<date>[\\d]{8})-(?<commit>[\\da-f]+).7z"
    },
    "autoupdate": {
        "architecture": {
            "64bit": {
                "url": "https://github.com/yuzu-emu/yuzu-mainline/releases/download/mainline-$version/yuzu-windows-msvc-$matchDate-$matchCommit.7z"
            }
        }
    }
}
