{
    "homepage": "https://yuzu-emu.org/",
    "version": "0-245",
    "license": "GPL-2.0-only",
    "architecture": {
        "64bit": {
            "url": "https://github.com/yuzu-emu/yuzu-mainline/releases/download/mainline-0-245/yuzu-windows-msvc-20200504-b4cdaa755.7z",
            "hash": "1cc58ec7fd89f60ae3d32371fd32b135e8d260b25ac52ff9e57234695c79c06d"
        }
    },
    "extract_dir": "yuzu-windows-msvc",
    "shortcuts": [
        [
            "yuzu.exe",
            "Yuzu"
        ]
    ],
    "checkver": {
        "github": "https://github.com/yuzu-emu/yuzu-mainline",
        "regex": "download/mainline-([\\d.-]+)/yuzu-windows-msvc-(?<date>[\\d]{8})-(?<commit>[\\da-f]+).7z"
    },
    "autoupdate": {
        "architecture": {
            "64bit": {
                "url": "https://github.com/yuzu-emu/yuzu-mainline/releases/download/mainline-$version/yuzu-windows-msvc-$matchDate-$matchCommit.7z"
            }
        }
    }
}
