{
    "version": "3078",
    "description": "Nintendo Switch emulator",
    "homepage": "https://github.com/pineappleEA/pineapple-src",
    "license": {
        "url": "https://github.com/pineappleEA/pineapple-src/blob/main/LICENSE",
        "identifier": "GPL-2.0"
    },
    "architecture": {
        "64bit": {
            "url": "https://github.com/pineappleEA/pineapple-src/releases/download/EA-3078/Windows-Yuzu-EA-3078.7z",
            "hash": "c1a3c0bc6274c4974927197ce78a2439d9160d57586813ae05c6403366c55645"
        }
    },
    "extract_dir": "yuzu-windows-msvc-early-access",
    "pre_install": [
        "if (!(Test-Path \"$persist_dir\")) {",
        "   New-item \"$persist_dir\" -ItemType Directory | Out-Null",
        "   New-item \"$persist_dir\\user\" -ItemType Directory | Out-Null",
        "   if (Test-Path \"$env:APPDATA\\yuzu\") {",
        "       Write-host \"Migrating AppData...\" -ForegroundColor yellow",
        "       Copy-Item -Path \"$env:APPDATA\\yuzu\\*\" -Destination \"$persist_dir\\user\" -Recurse",
        "       Remove-Item -Path \"$env:APPDATA\\yuzu\" -Recurse",
        "   }",
        "}"
    ],
    "bin": [
        [
            "yuzu.exe",
            "yuzu-dev"
        ],
        [
            "yuzu-cmd.exe",
            "yuzu-cmd-dev"
        ]
    ],
    "shortcuts": [
        [
            "yuzu.exe",
            "Yuzu (dev)"
        ]
    ],
    "persist": [
        "user",
        "plugins"
    ],
    "checkver": {
        "github": "https://github.com/pineappleEA/pineapple-src",
        "regex": "EA-(\\d+) \\(auto-updater\\)"
    },
    "autoupdate": {
        "architecture": {
            "64bit": {
                "url": "https://github.com/pineappleEA/pineapple-src/releases/download/EA-$version/Windows-Yuzu-EA-$version.7z"
            }
        }
    }
}
