{
    "homepage": "https://yuzu-emu.org/",
    "version": "0-510",
    "license": "GPL-2.0-only",
    "architecture": {
        "64bit": {
            "url": "https://github.com/yuzu-emu/yuzu-mainline/releases/download/mainline-0-510/yuzu-windows-msvc-20210118-db6a3d032.7z",
            "hash": "1d49efc1ff1d9e7d1bded261f46c62a444c1dae4d07c7817b5f49f5da5687770"
        }
    },
    "extract_dir": "yuzu-windows-msvc",
    "shortcuts": [
        [
            "yuzu.exe",
            "Yuzu"
        ]
    ],
    "checkver": {
        "github": "https://github.com/yuzu-emu/yuzu-mainline",
        "regex": "download/mainline-([\\d.-]+)/yuzu-windows-msvc-(?<date>[\\d]{8})-(?<commit>[\\da-f]+).7z"
    },
    "autoupdate": {
        "architecture": {
            "64bit": {
                "url": "https://github.com/yuzu-emu/yuzu-mainline/releases/download/mainline-$version/yuzu-windows-msvc-$matchDate-$matchCommit.7z"
            }
        }
    }
}
