{
    "homepage": "https://yuzu-emu.org/",
    "version": "0-288",
    "license": "GPL-2.0-only",
    "architecture": {
        "64bit": {
            "url": "https://github.com/yuzu-emu/yuzu-mainline/releases/download/mainline-0-288/yuzu-windows-msvc-20200620-365cb6fb2.7z",
            "hash": "cc3615ff82e3e60388699a315cd7d1c71cf40bee8568e1244c0f62bdbeb20d19"
        }
    },
    "extract_dir": "yuzu-windows-msvc",
    "shortcuts": [
        [
            "yuzu.exe",
            "Yuzu"
        ]
    ],
    "checkver": {
        "github": "https://github.com/yuzu-emu/yuzu-mainline",
        "regex": "download/mainline-([\\d.-]+)/yuzu-windows-msvc-(?<date>[\\d]{8})-(?<commit>[\\da-f]+).7z"
    },
    "autoupdate": {
        "architecture": {
            "64bit": {
                "url": "https://github.com/yuzu-emu/yuzu-mainline/releases/download/mainline-$version/yuzu-windows-msvc-$matchDate-$matchCommit.7z"
            }
        }
    }
}
