{
    "homepage": "http://cemu.info/",
    "version": "1.13.1d",
    "url": "http://cemu.info/releases/cemu_1.13.1.zip",
    "hash": "5fb86da5d5840d4a03bc75f4c86646f837312d4105ae499bd16aa4915cb77b7d",
    "extract_dir": "cemu_1.13.1",
    "shortcuts": [
        [
            "cemu.exe",
            "Cemu"
        ]
    ],
    "persist": [
        "settings.bin"
    ],
    "suggest": {
        "vcredist": [
            "extras/vcredist2015"
        ]
    },
    "checkver": {
        "re": "Download latest version \\(v((?<version>[\\d.]+)[\\w]*?),"
    },
    "autoupdate": {
        "url": "http://cemu.info/releases/cemu_$matchVersion.zip",
        "extract_dir": "cemu_$matchVersion"
    }
}
