{
    "homepage": "http://cemu.info/",
    "version": "1.12.1b",
    "url": "http://cemu.info/releases/cemu_1.12.1.zip",
    "hash": "063f13ee69aacc116bc5729064e4b864f591b32befe734fdd6ad706827611692",
    "extract_dir": "cemu_1.12.1",
    "shortcuts": [
        [
            "cemu.exe",
            "Cemu"
        ]
    ],
    "persist": [
        "settings.bin"
    ],
    "suggest": {
        "vcredist": [
            "extras/vcredist2015"
        ]
    },
    "checkver": {
        "re": "Download latest version \\(v((?<version>[\\d.]+)[\\w]*?),"
    },
    "autoupdate": {
        "url": "http://cemu.info/releases/cemu_$matchVersion.zip",
        "extract_dir": "cemu_$matchVersion"
    }
}
