{
    "homepage": "http://cemu.info/",
    "version": "1.12.0d",
    "url": "http://cemu.info/releases/cemu_1.12.0.zip",
    "hash": "20c167fe1942ae90bd25a2ea818c79a620c229b60019520b373e5a04cc7a1d53",
    "extract_dir": "cemu_1.12.0",
    "shortcuts": [
        [
            "cemu.exe",
            "Cemu"
        ]
    ],
    "persist": [
        "settings.bin"
    ],
    "suggest": {
        "vcredist": [
            "extras/vcredist2015"
        ]
    },
    "checkver": {
        "re": "Download latest version \\(v((?<version>[\\d.]+)[\\w]*?),"
    },
    "autoupdate": {
        "url": "http://cemu.info/releases/cemu_$matchVersion.zip",
        "extract_dir": "cemu_$matchVersion"
    }
}
