{
    "homepage": "https://yuzu-emu.org/",
    "version": "2299",
    "url": "https://github.com/yuzu-emu/yuzu-nightly/releases/download/nightly-2299/yuzu-windows-mingw-20191017-a21b88e.7z",
    "hash": "e6a6a4c81eabb4199a1c410c9db09c68f576fc246ca69c77de24ed175d62eabe",
    "extract_dir": "nightly-mingw",
    "shortcuts": [
        [
            "yuzu.exe",
            "Yuzu"
        ]
    ],
    "checkver": {
        "github": "https://github.com/yuzu-emu/yuzu-nightly",
        "re": "download/nightly-([\\d.]+)/yuzu-windows-mingw-(?<date>[\\d]{8})-(?<commit>[\\da-f]{7}).7z"
    },
    "autoupdate": {
        "url": "https://github.com/yuzu-emu/yuzu-nightly/releases/download/nightly-$version/yuzu-windows-mingw-$matchDate-$matchCommit.7z"
    }
}
