{
    "homepage": "https://yuzu-emu.org/",
    "version": "2372",
    "url": "https://github.com/yuzu-emu/yuzu-nightly/releases/download/nightly-2372/yuzu-windows-mingw-20191119-b0819e2.7z",
    "hash": "dba9fd74469491ad45946a4b434e13fa039de6ba638c1b1d26150565ccf664c1",
    "extract_dir": "nightly-mingw",
    "shortcuts": [
        [
            "yuzu.exe",
            "Yuzu"
        ]
    ],
    "checkver": {
        "github": "https://github.com/yuzu-emu/yuzu-nightly",
        "re": "download/nightly-([\\d.]+)/yuzu-windows-mingw-(?<date>[\\d]{8})-(?<commit>[\\da-f]{7}).7z"
    },
    "autoupdate": {
        "url": "https://github.com/yuzu-emu/yuzu-nightly/releases/download/nightly-$version/yuzu-windows-mingw-$matchDate-$matchCommit.7z"
    }
}
